{
  "ALREADY_ON_SERVER": "§6Core §8⇒ §fВы §cуже подключены §fк данному серверу",
  "SERVER_QUEUE": "§6Core §8⇒ §fВы были §6перенаправлены §fна сервер §5%s",
  "CORE_HELP": [
    "§f",
    "§6/core cmd сервер кмд §f- отправить команду на сервер §c(Только Bukkit)",
    "§6/core langreload §f- перезагрузить на всех серверах локализацию",
    "§6/core mem §f- вывести информацию о состоянии координатора",
    "§6/core gc §f- очистить кеш координатора",
    "§6/core stats §f- вывести статистику",
    "§6/core restart */@name/сервер §f- перезагрузить сервер §c(Только Bukkit)",
    "§6/core srv сервер §f- вывести информацию о сервере",
    "§6/core stop §f- отключить координатор §c(ЖЕЛАТЕЛЬНО НЕ ИСПОЛЬЗОВАТЬ)",
    "§f"
  ],
  "NOT_SERVER": "§6Core §8⇒ §fСервер §c%s §fне найден или не подключен к координатору!",
  "CORE_LANG_RELOAD_START": "§6Core §8⇒ §fПерезагружаю локализацию на всех серверах...",
  "CORE_LANG_RELOAD_ERROR": "§6Core §8⇒ §fЧто-то обосралось при перезагрузке локализации.",
  "CORE_LANG_RELOAD_SUCCESS": "§6Core §8⇒ §fВы успешно §6перезагрузили §fлокализацию",
  "CORE_MEM": [
    "§f",
    "§6Core §8⇒ §fИнформация о памяти",
    " §c- §fАптайм: §6%s",
    " §c- §fМаксимально: §6%sМБ",
    " §c- §fВыделено: §6%sМБ",
    " §c- §fСвободно: §6%sМБ",
    " §c- §fИспользуется: §6%sМБ",
    "§f"
  ],
  "CORE_GC": "§6Core §8⇒ §fКэш координатора успешно очищен",
  "CORE_STATS": [
    "§f",
    "§6Core §8⇒ §fИнформация о координаторе",
    " §5[СЕРВЕРА]",
    "  §c- §fBungee: §6%sшт",
    "  §c- §fBukkit: §6%sшт",
    "  §c- §fОнлайн: §6%s чел",
    " §5[МОДУЛИ]",
    "  §c- §fКол-во: §6%sшт",
    "  §c- §fВключено: §6%sшт",
    " §5[ПРОЧЕЕ]",
    "  §c- §fКоманд: §6%sшт",
    "  §c- §fПакетов: §6%sшт",
    "  §c- §fЗапущен: §6%s",
    "§f"
  ],
  "CORE_RESTART_ALL": "§6Core §8⇒ §fВы успешно §6перезагрузили §fвсе сервера",
  "CORE_RESTART_PREFIX_SUCCESS": "§6Core §8⇒ §fВы успешно §6перезагрузили §f%s серверов с префиксом §5%s",
  "CORE_RESTART_SUCCESS": "§6Core §8⇒ §fВы успешно §6перезагрузили §fсервер §5%s",
  "CORE_INFO_SERVER": [
    "§f",
    "§6Core §8⇒ §fИнформация о §5%s",
    " §c- §fНазвание: §6%s",
    " §c- §fТип: §6%s",
    " §c- §fОнлайн: §6%s",
    " §c- §fАйпи: §6%s",
    "§f"
  ],
  "BUTTON_RESTART": "§c[Перезагрузить]",
  "CLICK_TO_RESTART_SERVER": "§fЛКМ, чтобы перезагрузить",
  "BUTTON_TELEPORT": "§5[Телепорт]",
  "CLICK_TO_TELEPORT_SERVER": "§fЛКМ, чтобы телепортироваться",
  "GROUP_HELP": [
    "§f",
    "§6/group list §f- список групп",
    "§6/group get игрок §f- получить группу игрока",
    "§6/group set игрок нейм/лвл §f- установить группу игроку",
    "§6/group merge игрок игрок_2 §f- перенести группу на другой аккаунт",
    "§f"
  ],
  "GROUP_GET_NO_ARGS": "§6Core §8⇒ §fПолучить группу игрока - §6/group get игрок",
  "GROUP_GET_SUCCESS": "§6Core §8⇒ §fГруппа игрока §6%s §f- %s",
  "GROUP_SET_NO_ARGS": "§6Core §8⇒ §fУстановить группу игроку - §6/group set игрок нейм/лвл",
  "GROUP_SET_NO_FOUND": "§6Core §8⇒ §fГруппа не найдена",
  "GROUP_SET_ADMIN_ERROR": "§6Core §8⇒ §fВы §cне можете §fустановить группу администратора",
  "GROUP_SET_SUCCESS": "§6Core §8⇒ §fВы успешно §6установили §fигроку §5%s §fгруппу %s",
  "GROUP_MERGE_NO_ARGS": "§6Core §8⇒ §fПеренести группу игроку - §6/group merge игрок игрок_2",
  "GROUP_MERGE_ERROR": "§6Core §8⇒ §fИ смысл тебе переносить группу игрока? Ты бл*ть идиот?",
  "GROUP_MERGE_SUCCESS": "§6Core §8⇒ §fВы успешно §6перенесли §fгруппу %s §fна аккаунт §5%s",
  "MODULE_HELP": [
    "§f",
    "§6/module enable название §f- включить модуль",
    "§6/module disable название §f- отключить модуль",
    "§6/module reload название/* §f- перезагрузить модуль",
    "§6/module load название/* §f- загрузить модуль",
    "§6/module unload название/* §f- выгрузить модуль",
    "§6/module info название §f- информация о модуле",
    "§6/module list название §f- список модулей",
    "§f"
  ],
  "MODULE_UNKNOWN_COMMAND": "§6Core §8⇒ §fДанной субкоманды нет в модулях",
  "MODULE_ENABLE_NO_ARGS": "§6Core §8⇒ §fВключить модуль - §6/module enable название",
  "MODULE_DISABLE_NO_ARGS": "§6Core §8⇒ §fОтключить модуль - §6/module disable название",
  "MODULE_RELOAD_NO_ARGS": "§6Core §8⇒ §fПерезагрузить модуль - §6/module reload название/*",
  "MODULE_LOAD_NO_ARGS": "§6Core §8⇒ §fЗагрузить модуль - §6/module load название/*",
  "MODULE_UNLOAD_NO_ARGS": "§6Core §8⇒ §fОтгрузить модуль - §6/module unload название/*",
  "MODULE_INFO_NO_ARGS": "§6Core §8⇒ §fУзнать информацию о модуле - §6/module info название",
  "MODULE_NOT_FOUND": "§6Core §8⇒ §fМодуль §c%s §fне найден, список модулей - §6/modules",
  "MODULE_ALREADY_ENABLED": "§6Core §8⇒ §fМодуль §6%s §fуже включен",
  "MODULE_ENABLE_SUCCESS": "§6Core §8⇒ §fВы успешно §6включили §fмодуль §5%s",
  "MODULE_ALREADY_DISABLED": "§6Core §8⇒ §fМодуль §c%s §fуже выключен",
  "MODULE_DISABLE_SUCCESS": "§6Core §8⇒ §fВы успешно §cвыключили §fмодуль §5%s",
  "MODULE_RELOAD_ALL_SUCCESS": "§6Core §8⇒ §fВы успешно §6перезагрузили §fвсе модули",
  "MODULE_RELOAD_SUCCESS": "§6Core §8⇒ §fВы успешно §6перезагрузили §fмодуль §5%s",
  "MODULE_LOAD_ALL_SUCCESS": "§6Core §8⇒ §fВы успешно §6загрузили §fвсе модули",
  "MODULE_LOAD_SUCCESS": "§6Core §8⇒ §fВы успешно §6загрузили §fмодуль §5%s",
  "MODULE_UNLOAD_ALL_SUCCESS": "§6Core §8⇒ §fВы успешно §cотгрузили §fвсе модули",
  "MODULE_UNLOAD_SUCCESS": "§6Core §8⇒ §fВы успешно §cотгрузили §fмодуль §5%s",
  "MODULE_INFO": [
    "§f",
    "§fИнформация о модуле",
    " §c- §fНазвание: §6%s",
    " §c- §fАвторы: §6%s",
    " §c- §fЗависимости: §6%s",
    " §c- §fЗапущен: §6%s",
    " §c- §fСостояние: §6%s",
    "§f"
  ],
  "MODULE_LIST": "§6Core §8⇒ §fСписок модулей (§6%s§f): %s",
  "CORE_FIND_NO_ARGS": "§6Core §8⇒ §fНайти игрока - §6/find игрок",
  "CORE_FIND_LAST_ONLINE": "§6Core §8⇒ §fИгрок §6%s §fзаходил последний раз §c%s назад",
  "CORE_FIND_SUCCESS": "§6Core §8⇒ §fИгрок §6%s §fнаходится на сервере §5%s",
  "CORE_IPADDRESS": "§6Core §8⇒ §fУзнать IP игрока - §6/ip игрок",
  "CORE_IPADDRESS_SUCCESS": "§6Core §8⇒ §fАйпи игрока §6%s §f- §5%s",
  "CORE_GLOBAL_ONLINE": "§6Core §8⇒ §fОбщий онлайн - §6%s человек",
  "CORE_ONLINE_BY_PREFIX": "§6Core §8⇒ §fОнлайн серверов по префиксу §5@%s §fравен §6%s человек",
  "CORE_ONLINE_BY_SERVER": "§6Core §8⇒ §fОнлайн сервера §5%s §fравен §6%s человек",
  "CORE_SEND_NO_ARGS": "§6Core §8⇒ §fОтправить игрока на другой сервер - §6/send игрок сервер",
  "CORE_SEND_SENDER_SUCCESS": "§6Core §8⇒ §fВы успешно отправили игрока §6%s §fна сервер §5%s",
  "CORE_SEND_TARGET_SUCCESS": "§6Core §8⇒ §fАдминистратор %s §fотправил вас на сервер §5%s",
  "CORE_SERVER_NO_ARGS": "§6Core §8⇒ §fТелепортироваться на сервер - §6/server сервер",
  "CORE_THROW_NO_ARGS": "§6Core §8⇒ §fТелепортировать всех с одного на другой сервер - §6/throw сервер сервер_2",
  "CORE_THROW_SUCCESS": "§6Core §8⇒ §fВы успешно телепортировали всех с сервера §5%s §fна сервер §6%s",
  "CORE_WATCH_NO_ARGS": "§6Core §8⇒ §fСледить за игроком (телепортироваться к нему) - §6/watch игрок",
  "CORE_WATCH_ERROR_SPECTATE_YOURSELF": "§6Core §8⇒ §fВы §cне можете §fнаблюдать за собой",
  "CORE_WATCH_BROADCAST": "§6Core §8⇒ §6%s §fначал слежку за игроком §5%s"
}
